flightanalysis/__init__.py
flightanalysis/manoeuvre.py
flightanalysis/py.typed
flightanalysis/schedule.py
flightanalysis/version.py
flightanalysis/analysis/__init__.py
flightanalysis/analysis/el_analysis.py
flightanalysis/analysis/sch_analysis.py
flightanalysis/analysis/manoeuvre_analysis/__init__.py
flightanalysis/analysis/manoeuvre_analysis/alignment.py
flightanalysis/analysis/manoeuvre_analysis/analysis.py
flightanalysis/analysis/manoeuvre_analysis/basic.py
flightanalysis/analysis/manoeuvre_analysis/complete.py
flightanalysis/analysis/manoeuvre_analysis/scored.py
flightanalysis/base/ref_funcs.py
flightanalysis/base/utils.py
flightanalysis/builders/__init__.py
flightanalysis/builders/elbuilders.py
flightanalysis/builders/manbuilder.py
flightanalysis/builders/example/__init__.py
flightanalysis/builders/example/box.py
flightanalysis/builders/example/criteria.py
flightanalysis/builders/example/downgrades.py
flightanalysis/builders/example/manbuilder.py
flightanalysis/definition/__init__.py
flightanalysis/definition/collectors.py
flightanalysis/definition/dg_applicator.py
flightanalysis/definition/eldef.py
flightanalysis/definition/mandef.py
flightanalysis/definition/manoption.py
flightanalysis/definition/manparm.py
flightanalysis/definition/scheddef.py
flightanalysis/definition/operations/__init__.py
flightanalysis/definition/operations/funopp.py
flightanalysis/definition/operations/itemopp.py
flightanalysis/definition/operations/mathopp.py
flightanalysis/definition/operations/operation.py
flightanalysis/definition/operations/sumopp.py
flightanalysis/elements/__init__.py
flightanalysis/elements/element.py
flightanalysis/elements/line.py
flightanalysis/elements/loop.py
flightanalysis/elements/snap.py
flightanalysis/elements/spin.py
flightanalysis/elements/stall_turn.py
flightanalysis/elements/tail_slide.py
flightanalysis/scoring/__init__.py
flightanalysis/scoring/downgrade.py
flightanalysis/scoring/measurement.py
flightanalysis/scoring/reffuncs.py
flightanalysis-0.3.21.dist-info/METADATA
flightanalysis-0.3.21.dist-info/WHEEL
flightanalysis-0.3.21.dist-info/licenses/LICENSE
flightanalysis-0.3.21.dist-info/RECORD
